{
    "Wallpapers":
    [
	    {
			"url": "https://kdpixels.com/wallpapers/blue-marbles.jpg?raw=true",
			"thumbUrl": "https://kdpixels.com/wallpapers/blue-marbles-thumb.jpg?raw=true",
			"name": "Marbles"
	    },
	    {
			"url": "https://kdpixels.com/wallpapers/brooklyn-bridge.jpg?raw=true",
			"thumbUrl": "https://kdpixels.com/wallpapers/brooklyn-bridge-thumb.jpg?raw=true",
			"name": "Brooklyn Bridge"
		},
		{
			"url": "https://kdpixels.com/wallpapers/climbers.jpg?raw=true",
			"thumbUrl": "https://kdpixels.com/wallpapers/climbers-thumb.jpg?raw=true",
			"name": "Climbers"
		},
		{
			"url": "https://kdpixels.com/wallpapers/coffee-beans.jpg?raw=true",
			"thumbUrl": "https://kdpixels.com/wallpapers/coffee-beans-thumb.jpg?raw=true",
			"name": "Coffee Beans"
		},
		{
			"url": "https://kdpixels.com/wallpapers/fuji.jpg?raw=true",
			"thumbUrl": "https://kdpixels.com/wallpapers/fuji-thumb.jpg?raw=true",
			"name": "Fuji"
		},
		{
			"url": "https://kdpixels.com/wallpapers/hedge-greens.jpg?raw=true",
			"thumbUrl": "https://kdpixels.com/wallpapers/hedge-greens-thumb.jpg?raw=true",
			"name": "Hedge Greens"
		},
		{
			"url": "https://kdpixels.com/wallpapers/lumber-logs.jpg?raw=true",
			"thumbUrl": "https://kdpixels.com/wallpapers/lumber-logs-thumb.jpg?raw=true",
			"name": "Lumber Logs"
		},
		{
			"url": "https://kdpixels.com/wallpapers/moss-blur.jpg?raw=true",
			"thumbUrl": "https://kdpixels.com/wallpapers/moss-blur-thumb.jpg?raw=true",
			"name": "Moss Blur"
		},
		{
			"url": "https://kdpixels.com/wallpapers/moss-macro.jpg?raw=true",
			"thumbUrl": "https://kdpixels.com/wallpapers/moss-macro-thumb.jpg?raw=true",
			"name": "Moss Macro"
		},
		{
			"url": "https://kdpixels.com/wallpapers/pebbles.jpg?raw=true",
			"thumbUrl": "https://kdpixels.com/wallpapers/pebbles-thumb.jpg?raw=true",
			"name": "Pebbles"
		},
		{
			"url": "https://kdpixels.com/wallpapers/spring.jpg?raw=true",
			"thumbUrl": "https://kdpixels.com/wallpapers/spring-thumb.jpg?raw=true",
			"name": "Spring"
		},
		{
			"url": "https://kdpixels.com/wallpapers/starry-night.jpg?raw=true",
			"thumbUrl": "https://kdpixels.com/wallpapers/starry-night-thumb.jpg?raw=true",
			"name": "Starry Night"
		},
		{
			"url": "https://kdpixels.com/wallpapers/sunset.jpg?raw=true",
			"thumbUrl": "https://kdpixels.com/wallpapers/sunset-thumb.jpg?raw=true",
			"name": "Sunset"
		},
		{
			"url": "https://kdpixels.com/wallpapers/tulips.jpg?raw=true",
			"thumbUrl": "https://kdpixels.com/wallpapers/tulips-thumb.jpg?raw=true",
			"name": "Tulips"
		},
		{
			"url": "https://kdpixels.com/wallpapers/wular-lake.jpg?raw=true",
			"thumbUrl": "https://kdpixels.com/wallpapers/wular-lake-thumb.jpg?raw=true",
			"name": "Lake Wular"
		}
    ]
}